cmsrucio_import/__init__.py
cmsrucio_import/__main__.py
cmsrucio_import/main.py
cmsrucio_import/templates/dataset-upload.yml
cmsrucio_import/templates/file-upload.yml
cmsrucio_import-0.1.1.dist-info/WHEEL
cmsrucio_import-0.1.1.dist-info/METADATA
cmsrucio_import-0.1.1.dist-info/RECORD
