Metadata-Version: 2.1
Name: cmsrucio-import
Version: 0.1.1
Summary: Utility tool to upload files and datasets from local machine to rucio
Author: Rahul Chauhan
Author-email: rahul.chauhan@cern.ch
Requires-Python: >=3.6,<4.0
Classifier: Programming Language :: Python :: 3
Classifier: Programming Language :: Python :: 3.10
Classifier: Programming Language :: Python :: 3.6
Classifier: Programming Language :: Python :: 3.7
Classifier: Programming Language :: Python :: 3.8
Classifier: Programming Language :: Python :: 3.9
Requires-Dist: rucio-clients (>=1.28.3,<2.0.0)
Requires-Dist: strictyaml (>=1.6.1,<2.0.0)
Requires-Dist: typer (>=0.6.1,<0.7.0)
